cross_bones/__init__.py
cross_bones/_version.py
cross_bones/_version.pyi
cross_bones/align_catalogues.py
cross_bones/apply_shifts.py
cross_bones/catalogue.py
cross_bones/images.py
cross_bones/logging.py
cross_bones/matching.py
cross_bones/plotting.py
cross_bones/py.typed
cross_bones/shift_stats.py
cross_bones/unwise_align_catalogues.py
cross_bones-2.0.0.dist-info/METADATA
cross_bones-2.0.0.dist-info/WHEEL
cross_bones-2.0.0.dist-info/entry_points.txt
cross_bones-2.0.0.dist-info/licenses/LICENSE
cross_bones-2.0.0.dist-info/RECORD
